gdsbin/__init__.py
gdsbin/__main__.py
gdsbin/application.py
gdsbin/ast.py
gdsbin/callnew.py
gdsbin/classn.py
gdsbin/comment.py
gdsbin/defs.py
gdsbin/dictionaryname.py
gdsbin/extend.py
gdsbin/forloop.py
gdsbin/function.py
gdsbin/ifcond.py
gdsbin/key.py
gdsbin/keyword.py
gdsbin/parsertree.py
gdsbin/props.py
gdsbin/root.py
gdsbin/stringname.py
gdsbin/token.py
gdsbin/tokenizer.py
gdsbin/transpiler.py
gdsbin/variable.py
gdsbin/vector2.py
gdsbin/version.py
gdsbin/test/__init__.py
gdsbin/test/arrays_dictionaries_nested_const.py
gdsbin/test/benchmark.py
gdsbin/test/concatenation.py
gdsbin/test/function_default_parameter_type_inference.py
gdsbin/test/match_bind_unused.py
gdsbin/test/match_multiple_patterns_with_array.py
gdsbin/test/matches.py
gdsbin/test/multiline_arrays.py
gdsbin/test/nested_arithmetic.py
gdsbin/test/nested_array.py
gdsbin/test/nested_function_calls.py
gdsbin/test/nested_parentheses.py
gdsbin/test/operator_assign.py
gdsbin/test/semicolon_as_terminator.py
gdsbin/test/str_preserves_case.py
gdsbin/test/trailing_comma_in_function_args.py
gdsbin/test/typed_arrays.py
gdsbin/test/whiles.py
gdsbin-0.1.6.dist-info/licenses/LICENSE.md
gdsbin-0.1.6.dist-info/METADATA
gdsbin-0.1.6.dist-info/WHEEL
gdsbin-0.1.6.dist-info/top_level.txt
gdsbin-0.1.6.dist-info/zip-safe
gdsbin-0.1.6.dist-info/RECORD
