Metadata-Version: 2.4
Name: gdsbin
Version: 0.1.6
Summary: GDScript and Python runtime environment
Home-page: https://codeberg.org/LinuxUserGD/gdscript-transpiler-bin
Download-URL: https://linuxusergd.itch.io/gdscript-transpiler-bin
Author: LinuxUserGD
Author-email: hugegameartgd@gmail.com
License: MIT
Project-URL: Documentation, https://codeberg.org/LinuxUserGD/gdscript-transpiler-bin/wiki
Project-URL: Source, https://codeberg.org/LinuxUserGD/gdscript-transpiler-bin
Project-URL: Tracker, https://codeberg.org/LinuxUserGD/gdscript-transpiler-bin/issues
Classifier: Operating System :: MacOS :: MacOS X
Classifier: Operating System :: Microsoft :: Windows
Classifier: Operating System :: POSIX :: Linux
Classifier: Programming Language :: Python :: 2
Classifier: Programming Language :: Python :: 2.7
Classifier: Programming Language :: Python :: 3
Classifier: Programming Language :: Python :: 3.3
Classifier: Programming Language :: Python :: 3.4
Classifier: Programming Language :: Python :: 3.5
Classifier: Programming Language :: Python :: 3.6
Classifier: Programming Language :: Python :: 3.7
Classifier: Programming Language :: Python :: 3.8
Classifier: Programming Language :: Python :: 3.9
Classifier: Programming Language :: Python :: 3.10
Classifier: Programming Language :: Python :: 3.11
Classifier: Programming Language :: Python :: 3.12
Classifier: Programming Language :: Python :: 3.13
Classifier: Topic :: Software Development :: Libraries :: Python Modules
License-File: LICENSE.md
Dynamic: author
Dynamic: author-email
Dynamic: classifier
Dynamic: description
Dynamic: description-content-type
Dynamic: download-url
Dynamic: home-page
Dynamic: license
Dynamic: license-file
Dynamic: project-url
Dynamic: summary
